kc_ohlc/__init__.py
kc_ohlc/cli.py
kc_ohlc/client.py
kc_ohlc/exceptions.py
kc_ohlc-0.2.1.dist-info/METADATA
kc_ohlc-0.2.1.dist-info/WHEEL
kc_ohlc-0.2.1.dist-info/entry_points.txt
kc_ohlc-0.2.1.dist-info/top_level.txt
kc_ohlc-0.2.1.dist-info/RECORD
