Metadata-Version: 2.4
Name: kc-ohlc
Version: 0.2.1
Summary: Authenticated client + CLI for KC Trading OHLC API (pandas/polars). Optional HMAC signing.
Author-email: Karan Chavan <Karan80121@gmail.com>
License: MIT
Project-URL: Homepage, https://kctradings.com
Requires-Python: >=3.9
Requires-Dist: requests>=2.31.0
Requires-Dist: python-dateutil>=2.8.2
Provides-Extra: pandas
Requires-Dist: pandas>=2.0.0; extra == "pandas"
Provides-Extra: polars
Requires-Dist: polars>=1.1.0; extra == "polars"
